django_mapper/__init__.py
django_mapper/mapper.py
django_mapper-1.1.7.dist-info/LICENSE
django_mapper-1.1.7.dist-info/METADATA
django_mapper-1.1.7.dist-info/WHEEL
django_mapper-1.1.7.dist-info/top_level.txt
django_mapper-1.1.7.dist-info/RECORD
